{
	"_fullName": "xenolith/renderer/basic2d/glsl/XL2dShaders.h",
	"_kind": "file",
	"_name": "xenolith/renderer/basic2d/glsl/XL2dShaders.h",
	"childs": [{
		"_fullName": "XL2d.h",
		"_kind": "include directive",
		"_name": "XL2d.h",
		"id": 893802368,
		"include": "xenolith/renderer/basic2d/XL2d.h",
		"include_kind": "local",
		"kind": "include directive",
		"name": "XL2d.h"
	}, {
		"_fullName": "XENOLITH_RENDERER_BASIC2D_GLSL_XL2DSHADERS_H_",
		"_kind": "macro definition",
		"_name": "XENOLITH_RENDERER_BASIC2D_GLSL_XL2DSHADERS_H_",
		"id": 3503855647,
		"is_function_like": false,
		"is_object_like": true,
		"is_variadic": false,
		"kind": "macro definition",
		"name": "XENOLITH_RENDERER_BASIC2D_GLSL_XL2DSHADERS_H_",
		"replacement": ""
	}, {
		"_fullName": "::stappler",
		"_kind": "namespace",
		"_name": "stappler",
		"childs": [{
			"_fullName": "::stappler::xenolith",
			"_kind": "namespace",
			"_name": "xenolith",
			"childs": [{
				"_fullName": "::stappler::xenolith::basic2d",
				"_kind": "namespace",
				"_name": "basic2d",
				"childs": [{
					"_fullName": "::stappler::xenolith::basic2d::shaders",
					"_kind": "namespace",
					"_name": "shaders",
					"childs": [{
						"_fullName": "::stappler::xenolith::basic2d::shaders::MaterialFrag",
						"_kind": "variable",
						"_name": "MaterialFrag",
						"id": 25878889,
						"is_constexpr": false,
						"is_declaration": true,
						"is_definition": false,
						"kind": "variable",
						"name": "MaterialFrag",
						"semantic_scope": "",
						"storage_class": [
							"extern"
						],
						"type":  {
							"_typeName": "SpanView<uint32_t>",
							"arguments_exposed": false,
							"kind": "template_instantiation",
							"primary_template": {
								"name": "SpanView",
								"objects": [{
									"_fullName": "::stappler::SpanView<typename>",
									"_kind": "class template",
									"_name": "SpanView",
									"class": {
										"_fullName": "::stappler::SpanView<typename>",
										"_kind": "class",
										"_name": "SpanView",
										"class_kind": "class",
										"id": 2371948180,
										"is_declaration": false,
										"is_definition": true,
										"is_final": false,
										"kind": "class",
										"name": "SpanView",
										"scope": {
											"is_templated": true,
											"name": "SpanView",
											"template_parameters": [{
												"_fullName": "_Type",
												"_kind": "template type parameter",
												"_name": "_Type",
												"id": 1327381061,
												"is_variadic": false,
												"keyword": "typename",
												"kind": "template type parameter",
												"name": "_Type"
											}]
										},
										"semantic_scope": ""
									},
									"id": 2371948180,
									"kind": "class template",
									"name": "SpanView",
									"parameters": [{
										"_fullName": "_Type",
										"_kind": "template type parameter",
										"_name": "_Type",
										"id": 1327381061,
										"is_variadic": false,
										"keyword": "typename",
										"kind": "template type parameter",
										"name": "_Type"
									}],
									"scope":  {
										"is_templated": true,
										"name": "SpanView",
										"template_parameters": [{
											"_fullName": "_Type",
											"_kind": "template type parameter",
											"_name": "_Type",
											"id": 1327381061,
											"is_variadic": false,
											"keyword": "typename",
											"kind": "template type parameter",
											"name": "_Type"
										}]
									}
								}]
							},
							"unexposed_arguments": "uint32_t"
						}
					}, {
						"_fullName": "::stappler::xenolith::basic2d::shaders::MaterialVert",
						"_kind": "variable",
						"_name": "MaterialVert",
						"id": 1298629343,
						"is_constexpr": false,
						"is_declaration": true,
						"is_definition": false,
						"kind": "variable",
						"name": "MaterialVert",
						"semantic_scope": "",
						"storage_class": [
							"extern"
						],
						"type":  {
							"_typeName": "SpanView<uint32_t>",
							"arguments_exposed": false,
							"kind": "template_instantiation",
							"primary_template": {
								"name": "SpanView",
								"objects": [{
									"_fullName": "::stappler::SpanView<typename>",
									"_kind": "class template",
									"_name": "SpanView",
									"class": {
										"_fullName": "::stappler::SpanView<typename>",
										"_kind": "class",
										"_name": "SpanView",
										"class_kind": "class",
										"id": 2371948180,
										"is_declaration": false,
										"is_definition": true,
										"is_final": false,
										"kind": "class",
										"name": "SpanView",
										"scope": {
											"is_templated": true,
											"name": "SpanView",
											"template_parameters": [{
												"_fullName": "_Type",
												"_kind": "template type parameter",
												"_name": "_Type",
												"id": 1327381061,
												"is_variadic": false,
												"keyword": "typename",
												"kind": "template type parameter",
												"name": "_Type"
											}]
										},
										"semantic_scope": ""
									},
									"id": 2371948180,
									"kind": "class template",
									"name": "SpanView",
									"parameters": [{
										"_fullName": "_Type",
										"_kind": "template type parameter",
										"_name": "_Type",
										"id": 1327381061,
										"is_variadic": false,
										"keyword": "typename",
										"kind": "template type parameter",
										"name": "_Type"
									}],
									"scope":  {
										"is_templated": true,
										"name": "SpanView",
										"template_parameters": [{
											"_fullName": "_Type",
											"_kind": "template type parameter",
											"_name": "_Type",
											"id": 1327381061,
											"is_variadic": false,
											"keyword": "typename",
											"kind": "template type parameter",
											"name": "_Type"
										}]
									}
								}]
							},
							"unexposed_arguments": "uint32_t"
						}
					}, {
						"_fullName": "::stappler::xenolith::basic2d::shaders::SdfTrianglesComp",
						"_kind": "variable",
						"_name": "SdfTrianglesComp",
						"id": 1009690134,
						"is_constexpr": false,
						"is_declaration": true,
						"is_definition": false,
						"kind": "variable",
						"name": "SdfTrianglesComp",
						"semantic_scope": "",
						"storage_class": [
							"extern"
						],
						"type":  {
							"_typeName": "SpanView<uint32_t>",
							"arguments_exposed": false,
							"kind": "template_instantiation",
							"primary_template": {
								"name": "SpanView",
								"objects": [{
									"_fullName": "::stappler::SpanView<typename>",
									"_kind": "class template",
									"_name": "SpanView",
									"class": {
										"_fullName": "::stappler::SpanView<typename>",
										"_kind": "class",
										"_name": "SpanView",
										"class_kind": "class",
										"id": 2371948180,
										"is_declaration": false,
										"is_definition": true,
										"is_final": false,
										"kind": "class",
										"name": "SpanView",
										"scope": {
											"is_templated": true,
											"name": "SpanView",
											"template_parameters": [{
												"_fullName": "_Type",
												"_kind": "template type parameter",
												"_name": "_Type",
												"id": 1327381061,
												"is_variadic": false,
												"keyword": "typename",
												"kind": "template type parameter",
												"name": "_Type"
											}]
										},
										"semantic_scope": ""
									},
									"id": 2371948180,
									"kind": "class template",
									"name": "SpanView",
									"parameters": [{
										"_fullName": "_Type",
										"_kind": "template type parameter",
										"_name": "_Type",
										"id": 1327381061,
										"is_variadic": false,
										"keyword": "typename",
										"kind": "template type parameter",
										"name": "_Type"
									}],
									"scope":  {
										"is_templated": true,
										"name": "SpanView",
										"template_parameters": [{
											"_fullName": "_Type",
											"_kind": "template type parameter",
											"_name": "_Type",
											"id": 1327381061,
											"is_variadic": false,
											"keyword": "typename",
											"kind": "template type parameter",
											"name": "_Type"
										}]
									}
								}]
							},
							"unexposed_arguments": "uint32_t"
						}
					}, {
						"_fullName": "::stappler::xenolith::basic2d::shaders::SdfCirclesComp",
						"_kind": "variable",
						"_name": "SdfCirclesComp",
						"id": 1821289884,
						"is_constexpr": false,
						"is_declaration": true,
						"is_definition": false,
						"kind": "variable",
						"name": "SdfCirclesComp",
						"semantic_scope": "",
						"storage_class": [
							"extern"
						],
						"type":  {
							"_typeName": "SpanView<uint32_t>",
							"arguments_exposed": false,
							"kind": "template_instantiation",
							"primary_template": {
								"name": "SpanView",
								"objects": [{
									"_fullName": "::stappler::SpanView<typename>",
									"_kind": "class template",
									"_name": "SpanView",
									"class": {
										"_fullName": "::stappler::SpanView<typename>",
										"_kind": "class",
										"_name": "SpanView",
										"class_kind": "class",
										"id": 2371948180,
										"is_declaration": false,
										"is_definition": true,
										"is_final": false,
										"kind": "class",
										"name": "SpanView",
										"scope": {
											"is_templated": true,
											"name": "SpanView",
											"template_parameters": [{
												"_fullName": "_Type",
												"_kind": "template type parameter",
												"_name": "_Type",
												"id": 1327381061,
												"is_variadic": false,
												"keyword": "typename",
												"kind": "template type parameter",
												"name": "_Type"
											}]
										},
										"semantic_scope": ""
									},
									"id": 2371948180,
									"kind": "class template",
									"name": "SpanView",
									"parameters": [{
										"_fullName": "_Type",
										"_kind": "template type parameter",
										"_name": "_Type",
										"id": 1327381061,
										"is_variadic": false,
										"keyword": "typename",
										"kind": "template type parameter",
										"name": "_Type"
									}],
									"scope":  {
										"is_templated": true,
										"name": "SpanView",
										"template_parameters": [{
											"_fullName": "_Type",
											"_kind": "template type parameter",
											"_name": "_Type",
											"id": 1327381061,
											"is_variadic": false,
											"keyword": "typename",
											"kind": "template type parameter",
											"name": "_Type"
										}]
									}
								}]
							},
							"unexposed_arguments": "uint32_t"
						}
					}, {
						"_fullName": "::stappler::xenolith::basic2d::shaders::SdfRectsComp",
						"_kind": "variable",
						"_name": "SdfRectsComp",
						"id": 2946905336,
						"is_constexpr": false,
						"is_declaration": true,
						"is_definition": false,
						"kind": "variable",
						"name": "SdfRectsComp",
						"semantic_scope": "",
						"storage_class": [
							"extern"
						],
						"type":  {
							"_typeName": "SpanView<uint32_t>",
							"arguments_exposed": false,
							"kind": "template_instantiation",
							"primary_template": {
								"name": "SpanView",
								"objects": [{
									"_fullName": "::stappler::SpanView<typename>",
									"_kind": "class template",
									"_name": "SpanView",
									"class": {
										"_fullName": "::stappler::SpanView<typename>",
										"_kind": "class",
										"_name": "SpanView",
										"class_kind": "class",
										"id": 2371948180,
										"is_declaration": false,
										"is_definition": true,
										"is_final": false,
										"kind": "class",
										"name": "SpanView",
										"scope": {
											"is_templated": true,
											"name": "SpanView",
											"template_parameters": [{
												"_fullName": "_Type",
												"_kind": "template type parameter",
												"_name": "_Type",
												"id": 1327381061,
												"is_variadic": false,
												"keyword": "typename",
												"kind": "template type parameter",
												"name": "_Type"
											}]
										},
										"semantic_scope": ""
									},
									"id": 2371948180,
									"kind": "class template",
									"name": "SpanView",
									"parameters": [{
										"_fullName": "_Type",
										"_kind": "template type parameter",
										"_name": "_Type",
										"id": 1327381061,
										"is_variadic": false,
										"keyword": "typename",
										"kind": "template type parameter",
										"name": "_Type"
									}],
									"scope":  {
										"is_templated": true,
										"name": "SpanView",
										"template_parameters": [{
											"_fullName": "_Type",
											"_kind": "template type parameter",
											"_name": "_Type",
											"id": 1327381061,
											"is_variadic": false,
											"keyword": "typename",
											"kind": "template type parameter",
											"name": "_Type"
										}]
									}
								}]
							},
							"unexposed_arguments": "uint32_t"
						}
					}, {
						"_fullName": "::stappler::xenolith::basic2d::shaders::SdfRoundedRectsComp",
						"_kind": "variable",
						"_name": "SdfRoundedRectsComp",
						"id": 3116454558,
						"is_constexpr": false,
						"is_declaration": true,
						"is_definition": false,
						"kind": "variable",
						"name": "SdfRoundedRectsComp",
						"semantic_scope": "",
						"storage_class": [
							"extern"
						],
						"type":  {
							"_typeName": "SpanView<uint32_t>",
							"arguments_exposed": false,
							"kind": "template_instantiation",
							"primary_template": {
								"name": "SpanView",
								"objects": [{
									"_fullName": "::stappler::SpanView<typename>",
									"_kind": "class template",
									"_name": "SpanView",
									"class": {
										"_fullName": "::stappler::SpanView<typename>",
										"_kind": "class",
										"_name": "SpanView",
										"class_kind": "class",
										"id": 2371948180,
										"is_declaration": false,
										"is_definition": true,
										"is_final": false,
										"kind": "class",
										"name": "SpanView",
										"scope": {
											"is_templated": true,
											"name": "SpanView",
											"template_parameters": [{
												"_fullName": "_Type",
												"_kind": "template type parameter",
												"_name": "_Type",
												"id": 1327381061,
												"is_variadic": false,
												"keyword": "typename",
												"kind": "template type parameter",
												"name": "_Type"
											}]
										},
										"semantic_scope": ""
									},
									"id": 2371948180,
									"kind": "class template",
									"name": "SpanView",
									"parameters": [{
										"_fullName": "_Type",
										"_kind": "template type parameter",
										"_name": "_Type",
										"id": 1327381061,
										"is_variadic": false,
										"keyword": "typename",
										"kind": "template type parameter",
										"name": "_Type"
									}],
									"scope":  {
										"is_templated": true,
										"name": "SpanView",
										"template_parameters": [{
											"_fullName": "_Type",
											"_kind": "template type parameter",
											"_name": "_Type",
											"id": 1327381061,
											"is_variadic": false,
											"keyword": "typename",
											"kind": "template type parameter",
											"name": "_Type"
										}]
									}
								}]
							},
							"unexposed_arguments": "uint32_t"
						}
					}, {
						"_fullName": "::stappler::xenolith::basic2d::shaders::SdfPolygonsComp",
						"_kind": "variable",
						"_name": "SdfPolygonsComp",
						"id": 1803886256,
						"is_constexpr": false,
						"is_declaration": true,
						"is_definition": false,
						"kind": "variable",
						"name": "SdfPolygonsComp",
						"semantic_scope": "",
						"storage_class": [
							"extern"
						],
						"type":  {
							"_typeName": "SpanView<uint32_t>",
							"arguments_exposed": false,
							"kind": "template_instantiation",
							"primary_template": {
								"name": "SpanView",
								"objects": [{
									"_fullName": "::stappler::SpanView<typename>",
									"_kind": "class template",
									"_name": "SpanView",
									"class": {
										"_fullName": "::stappler::SpanView<typename>",
										"_kind": "class",
										"_name": "SpanView",
										"class_kind": "class",
										"id": 2371948180,
										"is_declaration": false,
										"is_definition": true,
										"is_final": false,
										"kind": "class",
										"name": "SpanView",
										"scope": {
											"is_templated": true,
											"name": "SpanView",
											"template_parameters": [{
												"_fullName": "_Type",
												"_kind": "template type parameter",
												"_name": "_Type",
												"id": 1327381061,
												"is_variadic": false,
												"keyword": "typename",
												"kind": "template type parameter",
												"name": "_Type"
											}]
										},
										"semantic_scope": ""
									},
									"id": 2371948180,
									"kind": "class template",
									"name": "SpanView",
									"parameters": [{
										"_fullName": "_Type",
										"_kind": "template type parameter",
										"_name": "_Type",
										"id": 1327381061,
										"is_variadic": false,
										"keyword": "typename",
										"kind": "template type parameter",
										"name": "_Type"
									}],
									"scope":  {
										"is_templated": true,
										"name": "SpanView",
										"template_parameters": [{
											"_fullName": "_Type",
											"_kind": "template type parameter",
											"_name": "_Type",
											"id": 1327381061,
											"is_variadic": false,
											"keyword": "typename",
											"kind": "template type parameter",
											"name": "_Type"
										}]
									}
								}]
							},
							"unexposed_arguments": "uint32_t"
						}
					}, {
						"_fullName": "::stappler::xenolith::basic2d::shaders::SdfShadowsFrag",
						"_kind": "variable",
						"_name": "SdfShadowsFrag",
						"id": 4012144300,
						"is_constexpr": false,
						"is_declaration": true,
						"is_definition": false,
						"kind": "variable",
						"name": "SdfShadowsFrag",
						"semantic_scope": "",
						"storage_class": [
							"extern"
						],
						"type":  {
							"_typeName": "SpanView<uint32_t>",
							"arguments_exposed": false,
							"kind": "template_instantiation",
							"primary_template": {
								"name": "SpanView",
								"objects": [{
									"_fullName": "::stappler::SpanView<typename>",
									"_kind": "class template",
									"_name": "SpanView",
									"class": {
										"_fullName": "::stappler::SpanView<typename>",
										"_kind": "class",
										"_name": "SpanView",
										"class_kind": "class",
										"id": 2371948180,
										"is_declaration": false,
										"is_definition": true,
										"is_final": false,
										"kind": "class",
										"name": "SpanView",
										"scope": {
											"is_templated": true,
											"name": "SpanView",
											"template_parameters": [{
												"_fullName": "_Type",
												"_kind": "template type parameter",
												"_name": "_Type",
												"id": 1327381061,
												"is_variadic": false,
												"keyword": "typename",
												"kind": "template type parameter",
												"name": "_Type"
											}]
										},
										"semantic_scope": ""
									},
									"id": 2371948180,
									"kind": "class template",
									"name": "SpanView",
									"parameters": [{
										"_fullName": "_Type",
										"_kind": "template type parameter",
										"_name": "_Type",
										"id": 1327381061,
										"is_variadic": false,
										"keyword": "typename",
										"kind": "template type parameter",
										"name": "_Type"
									}],
									"scope":  {
										"is_templated": true,
										"name": "SpanView",
										"template_parameters": [{
											"_fullName": "_Type",
											"_kind": "template type parameter",
											"_name": "_Type",
											"id": 1327381061,
											"is_variadic": false,
											"keyword": "typename",
											"kind": "template type parameter",
											"name": "_Type"
										}]
									}
								}]
							},
							"unexposed_arguments": "uint32_t"
						}
					}, {
						"_fullName": "::stappler::xenolith::basic2d::shaders::SdfShadowsVert",
						"_kind": "variable",
						"_name": "SdfShadowsVert",
						"id": 320132829,
						"is_constexpr": false,
						"is_declaration": true,
						"is_definition": false,
						"kind": "variable",
						"name": "SdfShadowsVert",
						"semantic_scope": "",
						"storage_class": [
							"extern"
						],
						"type":  {
							"_typeName": "SpanView<uint32_t>",
							"arguments_exposed": false,
							"kind": "template_instantiation",
							"primary_template": {
								"name": "SpanView",
								"objects": [{
									"_fullName": "::stappler::SpanView<typename>",
									"_kind": "class template",
									"_name": "SpanView",
									"class": {
										"_fullName": "::stappler::SpanView<typename>",
										"_kind": "class",
										"_name": "SpanView",
										"class_kind": "class",
										"id": 2371948180,
										"is_declaration": false,
										"is_definition": true,
										"is_final": false,
										"kind": "class",
										"name": "SpanView",
										"scope": {
											"is_templated": true,
											"name": "SpanView",
											"template_parameters": [{
												"_fullName": "_Type",
												"_kind": "template type parameter",
												"_name": "_Type",
												"id": 1327381061,
												"is_variadic": false,
												"keyword": "typename",
												"kind": "template type parameter",
												"name": "_Type"
											}]
										},
										"semantic_scope": ""
									},
									"id": 2371948180,
									"kind": "class template",
									"name": "SpanView",
									"parameters": [{
										"_fullName": "_Type",
										"_kind": "template type parameter",
										"_name": "_Type",
										"id": 1327381061,
										"is_variadic": false,
										"keyword": "typename",
										"kind": "template type parameter",
										"name": "_Type"
									}],
									"scope":  {
										"is_templated": true,
										"name": "SpanView",
										"template_parameters": [{
											"_fullName": "_Type",
											"_kind": "template type parameter",
											"_name": "_Type",
											"id": 1327381061,
											"is_variadic": false,
											"keyword": "typename",
											"kind": "template type parameter",
											"name": "_Type"
										}]
									}
								}]
							},
							"unexposed_arguments": "uint32_t"
						}
					}, {
						"_fullName": "::stappler::xenolith::basic2d::shaders::SdfImageComp",
						"_kind": "variable",
						"_name": "SdfImageComp",
						"id": 483758312,
						"is_constexpr": false,
						"is_declaration": true,
						"is_definition": false,
						"kind": "variable",
						"name": "SdfImageComp",
						"semantic_scope": "",
						"storage_class": [
							"extern"
						],
						"type":  {
							"_typeName": "SpanView<uint32_t>",
							"arguments_exposed": false,
							"kind": "template_instantiation",
							"primary_template": {
								"name": "SpanView",
								"objects": [{
									"_fullName": "::stappler::SpanView<typename>",
									"_kind": "class template",
									"_name": "SpanView",
									"class": {
										"_fullName": "::stappler::SpanView<typename>",
										"_kind": "class",
										"_name": "SpanView",
										"class_kind": "class",
										"id": 2371948180,
										"is_declaration": false,
										"is_definition": true,
										"is_final": false,
										"kind": "class",
										"name": "SpanView",
										"scope": {
											"is_templated": true,
											"name": "SpanView",
											"template_parameters": [{
												"_fullName": "_Type",
												"_kind": "template type parameter",
												"_name": "_Type",
												"id": 1327381061,
												"is_variadic": false,
												"keyword": "typename",
												"kind": "template type parameter",
												"name": "_Type"
											}]
										},
										"semantic_scope": ""
									},
									"id": 2371948180,
									"kind": "class template",
									"name": "SpanView",
									"parameters": [{
										"_fullName": "_Type",
										"_kind": "template type parameter",
										"_name": "_Type",
										"id": 1327381061,
										"is_variadic": false,
										"keyword": "typename",
										"kind": "template type parameter",
										"name": "_Type"
									}],
									"scope":  {
										"is_templated": true,
										"name": "SpanView",
										"template_parameters": [{
											"_fullName": "_Type",
											"_kind": "template type parameter",
											"_name": "_Type",
											"id": 1327381061,
											"is_variadic": false,
											"keyword": "typename",
											"kind": "template type parameter",
											"name": "_Type"
										}]
									}
								}]
							},
							"unexposed_arguments": "uint32_t"
						}
					}],
					"id": 358775330,
					"is_anonymous": false,
					"is_inline": false,
					"is_nested": true,
					"kind": "namespace",
					"name": "shaders",
					"scope": {
						"name": "shaders"
					}
				}],
				"id": 245581775,
				"is_anonymous": false,
				"is_inline": false,
				"is_nested": true,
				"kind": "namespace",
				"name": "basic2d",
				"scope": {
					"name": "basic2d"
				}
			}],
			"id": 2324754634,
			"is_anonymous": false,
			"is_inline": false,
			"is_nested": true,
			"kind": "namespace",
			"name": "xenolith",
			"scope": {
				"name": "xenolith"
			}
		}],
		"id": 96045446,
		"is_anonymous": false,
		"is_inline": false,
		"is_nested": false,
		"kind": "namespace",
		"name": "stappler",
		"scope": {
			"name": "stappler"
		}
	}],
	"id": 4238959563,
	"kind": "file",
	"name": "xenolith/renderer/basic2d/glsl/XL2dShaders.h",
	"unmatched_comments": [{
		"line": 21,
		"text": "\nCopyright (c) 2023 Stappler LLC <admin@stappler.dev>\n\nPermission is hereby granted, free of charge, to any person obtaining a copy\nof this software and associated documentation files (the \"Software\"), to deal\nin the Software without restriction, including without limitation the rights\nto use, copy, modify, merge, publish, distribute, sublicense, and/or sell\ncopies of the Software, and to permit persons to whom the Software is\nfurnished to do so, subject to the following conditions:\n\nThe above copyright notice and this permission notice shall be included in\nall copies or substantial portions of the Software.\n\nTHE SOFTWARE IS PROVIDED \"AS IS\", WITHOUT WARRANTY OF ANY KIND, EXPRESS OR\nIMPLIED, INCLUDING BUT NOT LIMITED TO THE WARRANTIES OF MERCHANTABILITY,\nFITNESS FOR A PARTICULAR PURPOSE AND NONINFRINGEMENT. IN NO EVENT SHALL THE\nAUTHORS OR COPYRIGHT HOLDERS BE LIABLE FOR ANY CLAIM, DAMAGES OR OTHER\nLIABILITY, WHETHER IN AN ACTION OF CONTRACT, TORT OR OTHERWISE, ARISING FROM,\nOUT OF OR IN CONNECTION WITH THE SOFTWARE OR THE USE OR OTHER DEALINGS IN\nTHE SOFTWARE.\n"
	}]
}